Metadata-Version: 2.1
Name: Pygitcli
Version: 0.0.6
Summary: Run git terminal commands from python scripts
Home-page: https://github.com/antrikshmisri/Pygit
Author: Antriksh Misri
Author-email: antrikshmisri@gmail.com
License: MIT
Keywords: git
Platform: UNKNOWN
Classifier: Development Status :: 5 - Production/Stable
Classifier: Intended Audience :: Education
Classifier: Operating System :: Microsoft :: Windows :: Windows 10
Classifier: License :: OSI Approved :: MIT License
Classifier: Programming Language :: Python :: 3
